{"is_source_file": true, "format": "TypeScript / TSX", "description": "This file defines the root layout component for a Next.js application, configuring fonts, metadata, and wrapping the application with context providers for authentication and modal management.", "external_files": ["./globals.css", "../contexts/AuthContext", "../contexts/ModalContext"], "external_methods": ["NextFont.Geist", "NextFont.Geist_Mono"], "published": ["metadata"], "classes": [], "methods": [{"name": "RootLayout", "description": "React component that sets up the application's overall layout, including font styling, metadata, and context providers."}], "calls": ["Geist", "Geist_Mono", "AuthProvider", "ModalProvider"], "search-terms": ["React layout component", "Next.js metadata", "font configuration", "AuthContext", "ModalContext", "layout.tsx"], "state": 2, "file_id": 5, "knowledge_revision": 51, "git_revision": "d22844859d3d462f628c1e153de0f6050f34d9c4", "revision_history": [{"21": "f7396513230bf17f01d475f8a9da028285632c6e"}, {"51": "d22844859d3d462f628c1e153de0f6050f34d9c4"}], "ctags": [], "hash": "2434d87dad25ac4a20e9de54b009e194", "format-version": 4, "code-base-name": "notes_frontend", "filename": "notes_frontend/src/app/layout.tsx"}